{
  "timestamp": "2025-09-25T16:46:58.631563+00:00",
  "source": "microsoft",
  "type": "email",
  "message": "New email from Cerebral Valley: Announcing our LA Tech Week Afterparty, 10/16 \ud83e\udd42",
  "metadata": {
    "account": "elio@pascarelli.com",
    "subject": "Announcing our LA Tech Week Afterparty, 10/16 \ud83e\udd42",
    "sender_name": "Cerebral Valley",
    "sender_address": "cerebralvalley@mail.beehiiv.com",
    "preview": "Co-hosted with Nebius at the iconic Delilah in West Hollywood. RSVPs live!  \u200c \u200c \u200c \u200c \u200c \u200c \u200c \u200c \u200c \u200c \u200c \u200c \u200c \u200c \u200c \u200c \u200c \u200c \u200c \u200c \u200c \u200c \u200c \u200c \u200c \u200c \u200c \u200c \u200c \u200c \u200c \u200c \u200c \u200c \u200c \u200c \u200c \u200c \u200c \u200c \u200c \u200c \u200c \u200c \u200c \u200c \u200c \u200c \u200c \u200c \u200c \u200c \u200c \u200c \u200c \u200c \u200c \u200c \u200c \u200c \u200c \u200c ",
    "received_at": "2025-09-25T16:45:58Z"
  }
}