{
  "18862cb0": {
    "message": "send elio his weekly monday briefing on whatsapp - calendar events, emails to respond to, tasks, deadlines",
    "schedule_type": "weekly on monday at 09:00",
    "next_run": "2025-09-22T09:00:00+01:00"
  },
  "a0847fb8": {
    "message": "text 351914173970 back",
    "schedule_type": "once (in 20.0 minutes)",
    "next_run": "2025-09-17T11:25:59.774514"
  },
  "368f0910": {
    "message": "send banana to elio on whatsapp",
    "schedule_type": "once (in 1.0 minute)",
    "next_run": "2025-09-17T11:10:17.349461"
  }
}